gpt_cli/__init__.py
matteing_gpt_cli-0.1.1.dist-info/entry_points.txt
matteing_gpt_cli-0.1.1.dist-info/WHEEL
matteing_gpt_cli-0.1.1.dist-info/METADATA
matteing_gpt_cli-0.1.1.dist-info/RECORD
